CHANGELOG.txt
LICENSE.txt
MANIFEST.in
README.txt
setup.cfg
setup.py
ruphonetic/__init__.py
ruphonetic/transcriptor.py
ruphonetic/utils.py
ruphonetic.egg-info/PKG-INFO
ruphonetic.egg-info/SOURCES.txt
ruphonetic.egg-info/dependency_links.txt
ruphonetic.egg-info/requires.txt
ruphonetic.egg-info/top_level.txt
ruphonetic/accentuation/__init__.py
ruphonetic/accentuation/lemmas.dat
ruphonetic/accentuation/stress.py
ruphonetic/accentuation/wordforms.dat